MambuPy/__init__.py
MambuPy/mambuconfig.py
MambuPy/mambugeturl.py
MambuPy/mambuutil.py
MambuPy/api/__init__.py
MambuPy/api/classes.py
MambuPy/api/entities.py
MambuPy/api/interfaces.py
MambuPy/api/mambubranch.py
MambuPy/api/mambucentre.py
MambuPy/api/mambuclient.py
MambuPy/api/mambucustomfield.py
MambuPy/api/mambugroup.py
MambuPy/api/mambuloan.py
MambuPy/api/mambuproduct.py
MambuPy/api/mamburole.py
MambuPy/api/mambustruct.py
MambuPy/api/mambutask.py
MambuPy/api/mambutransaction.py
MambuPy/api/mambuuser.py
MambuPy/api/vos.py
MambuPy/api/connector/__init__.py
MambuPy/api/connector/mambuconnector.py
MambuPy/api/connector/rest.py
MambuPy/orm/__init__.py
MambuPy/orm/schema_activities.py
MambuPy/orm/schema_addresses.py
MambuPy/orm/schema_branches.py
MambuPy/orm/schema_centres.py
MambuPy/orm/schema_clients.py
MambuPy/orm/schema_customfields.py
MambuPy/orm/schema_dummies.py
MambuPy/orm/schema_groups.py
MambuPy/orm/schema_loans.py
MambuPy/orm/schema_mambu.py
MambuPy/orm/schema_orm.py
MambuPy/orm/schema_tasks.py
MambuPy/orm/schema_users.py
MambuPy/rest/__init__.py
MambuPy/rest/mambuactivity.py
MambuPy/rest/mambubranch.py
MambuPy/rest/mambucentre.py
MambuPy/rest/mambuclient.py
MambuPy/rest/mambugroup.py
MambuPy/rest/mambuloan.py
MambuPy/rest/mambuproduct.py
MambuPy/rest/mamburepayment.py
MambuPy/rest/mamburestutils.py
MambuPy/rest/mamburoles.py
MambuPy/rest/mambusaving.py
MambuPy/rest/mambusavingfundingrepayment.py
MambuPy/rest/mambusavingtransaction.py
MambuPy/rest/mambustruct.py
MambuPy/rest/mambutask.py
MambuPy/rest/mambutransaction.py
MambuPy/rest/mambutransactionchannel.py
MambuPy/rest/mambuuser.py
MambuPy/utils/__init__.py
MambuPy/utils/userdeactivate.py
mambupy/__init__.py
mambupy/mambuconfig.py
mambupy/mambugeturl.py
mambupy/mambuutil.py
mambupy/api/__init__.py
mambupy/api/classes.py
mambupy/api/entities.py
mambupy/api/interfaces.py
mambupy/api/mambubranch.py
mambupy/api/mambucentre.py
mambupy/api/mambuclient.py
mambupy/api/mambucustomfield.py
mambupy/api/mambugroup.py
mambupy-2.1.1.dist-info/licenses/LICENSE
mambupy-2.1.1.dist-info/METADATA
mambupy-2.1.1.dist-info/WHEEL
mambupy-2.1.1.dist-info/top_level.txt
mambupy-2.1.1.dist-info/RECORD
