Metadata-Version: 2.4
Name: MambuPy
Version: 2.1.1
Summary: A python library for using Mambu APIs.
Author-email: "Javier Novoa C." <jstitch@gmail.com>
License: LICENSE
Project-URL: Homepage, https://mambupydocs.readthedocs.io
Project-URL: Documentation, https://mambupydocs.readthedocs.io
Project-URL: Repository, https://gitlab.com/jstitch/mambupy
Project-URL: Issues, https://gitlab.com/jstitch/mambupy/-/issues
Project-URL: Changelog, https://gitlab.com/jstitch/mambupy/-/raw/master/CHANGELOG
Keywords: mambu
Classifier: Development Status :: 5 - Production/Stable
Classifier: Intended Audience :: Developers
Classifier: Intended Audience :: Financial and Insurance Industry
Classifier: License :: OSI Approved :: GNU General Public License v3 or later (GPLv3+)
Classifier: Operating System :: OS Independent
Classifier: Programming Language :: Python :: 3
Classifier: Topic :: Software Development :: Libraries :: Python Modules
Requires-Python: >=3.7
License-File: LICENSE
Requires-Dist: PyYAML==6.0.1
Requires-Dist: requests==2.31.0
Requires-Dist: requests_toolbelt==1.0.0
Requires-Dist: dateutils==0.6.12
Provides-Extra: full
Requires-Dist: SQLAlchemy==1.3.6; extra == "full"
Requires-Dist: mysqlclient==2.1.0; extra == "full"
Provides-Extra: doc
Requires-Dist: sphinx==5.0.0; extra == "doc"
Requires-Dist: sphinx_rtd_theme; extra == "doc"
Provides-Extra: dev
Requires-Dist: freezegun==1.1.0; extra == "dev"
Requires-Dist: mock; extra == "dev"
Requires-Dist: coverage; extra == "dev"
Requires-Dist: pylint; extra == "dev"
Requires-Dist: ruff; extra == "dev"
Requires-Dist: black; extra == "dev"
Requires-Dist: isort; extra == "dev"
Provides-Extra: deploy
Requires-Dist: build; extra == "deploy"
Requires-Dist: twine; extra == "deploy"
Provides-Extra: devtools
Requires-Dist: ipython; extra == "devtools"
Requires-Dist: ipdb; extra == "devtools"
Requires-Dist: devpi-client>=7.2.0; extra == "devtools"
Dynamic: license-file
